pyftools/__init__.py
pyftools/file.py
pyftools/text.py
pyftools-0.0.3.dist-info/LICENSE
pyftools-0.0.3.dist-info/METADATA
pyftools-0.0.3.dist-info/WHEEL
pyftools-0.0.3.dist-info/top_level.txt
pyftools-0.0.3.dist-info/RECORD
