Metadata-Version: 2.1
Name: pyftools
Version: 0.0.3
Summary: python file tools is a simple file and text processing library with batch documents.
Home-page: https://github.com/hzcx998/pyftools
Author: Jason Hu
Author-email: 2323168280@qq.com
License: MIT
Platform: UNKNOWN
Classifier: License :: OSI Approved :: MIT License
Classifier: Programming Language :: Python
Classifier: Programming Language :: Python :: 2
Classifier: Programming Language :: Python :: 2.7
Classifier: Programming Language :: Python :: 3
Classifier: Programming Language :: Python :: 3.7
Classifier: Programming Language :: Python :: Implementation :: CPython
Classifier: Programming Language :: Python :: Implementation :: PyPy
